satindex/__init__.py
satindex/satellite_image.py
satindex-0.1.0.dist-info/LICENSE
satindex-0.1.0.dist-info/METADATA
satindex-0.1.0.dist-info/NOTICE
satindex-0.1.0.dist-info/WHEEL
satindex-0.1.0.dist-info/top_level.txt
satindex-0.1.0.dist-info/RECORD
